{
	"animations": [
		{
			"offsets": [
				2,
				1
			],
			"loop": false,
			"fps": 24,
			"anim": "idle",
			"indices": [],
			"name": "idle"
		},
		{
			"offsets": [
				0,
				0
			],
			"loop": false,
			"fps": 24,
			"anim": "singUPmiss",
			"indices": [],
			"name": "miss up"
		},
		{
			"offsets": [
				0,
				0
			],
			"loop": false,
			"fps": 24,
			"anim": "singDOWNmiss",
			"indices": [],
			"name": "miss down"
		},
		{
			"offsets": [
				0,
				0
			],
			"loop": false,
			"fps": 24,
			"anim": "singRIGHTmiss",
			"indices": [],
			"name": "miss right"
		},
		{
			"offsets": [
				0,
				0
			],
			"loop": false,
			"fps": 24,
			"anim": "singLEFTmiss",
			"indices": [],
			"name": "miss left"
		},
		{
			"offsets": [
				0,
				0
			],
			"loop": false,
			"fps": 30,
			"anim": "singLEFT",
			"indices": [],
			"name": "left"
		},
		{
			"offsets": [
				0,
				0
			],
			"loop": false,
			"fps": 30,
			"anim": "singDOWN",
			"indices": [],
			"name": "down"
		},
		{
			"offsets": [
				0,
				0
			],
			"loop": false,
			"fps": 30,
			"anim": "singUP",
			"indices": [],
			"name": "up"
		},
		{
			"offsets": [
				0,
				0
			],
			"loop": false,
			"fps": 30,
			"anim": "singRIGHT",
			"indices": [],
			"name": "right"
		},
		{
			"offsets": [
				0,
				0
			],
			"loop": false,
			"fps": 24,
			"anim": "firstDeath",
			"indices": [],
			"name": "death"
		},
		{
			"offsets": [
				0,
				0
			],
			"loop": true,
			"fps": 24,
			"anim": "deathLoop",
			"indices": [],
			"name": "loop"
		},
		{
			"offsets": [
				0,
				0
			],
			"loop": false,
			"fps": 24,
			"anim": "deathConfirm",
			"indices": [],
			"name": "retry"
		}
	],
	"no_antialiasing": false,
	"image": "characters/bf/driver bf",
	"position": [
		120,
		360
	],
	"healthicon": "bf driver",
	"flip_x": true,
	"healthbar_colors": [
		51,
		153,
		204
	],
	"camera_position": [
		80,
		-50
	],
	"sing_duration": 6.1,
	"scale": 2.5
}